amsterdam_schema_tools-9.1.6.dist-info/licenses/LICENSE
schematools/__init__.py
schematools/_utils.py
schematools/cli.py
schematools/exceptions.py
schematools/factories.py
schematools/loaders.py
schematools/naming.py
schematools/types.py
schematools/validation.py
schematools/ckan/__init__.py
schematools/ckan/_convert.py
schematools/contrib/__init__.py
schematools/contrib/django/__init__.py
schematools/contrib/django/app_config.py
schematools/contrib/django/apps.py
schematools/contrib/django/auth_backend.py
schematools/contrib/django/cli.py
schematools/contrib/django/db.py
schematools/contrib/django/factories.py
schematools/contrib/django/loaders.py
schematools/contrib/django/managers.py
schematools/contrib/django/mockers.py
schematools/contrib/django/models.py
schematools/contrib/django/signals.py
schematools/contrib/django/validators.py
schematools/contrib/django/faker/__init__.py
schematools/contrib/django/faker/create.py
schematools/contrib/django/faker/relate.py
schematools/contrib/django/faker/providers/__init__.py
schematools/contrib/django/faker/providers/date.py
schematools/contrib/django/faker/providers/date_time.py
schematools/contrib/django/faker/providers/geo.py
schematools/contrib/django/faker/providers/integer.py
schematools/contrib/django/faker/providers/nuller.py
schematools/contrib/django/faker/providers/pyfloat.py
schematools/contrib/django/management/__init__.py
schematools/contrib/django/management/commands/__init__.py
schematools/contrib/django/management/commands/change_dataset.py
schematools/contrib/django/management/commands/create_mock_data.py
schematools/contrib/django/management/commands/create_tables.py
schematools/contrib/django/management/commands/create_views.py
schematools/contrib/django/management/commands/dump_model_mockers.py
schematools/contrib/django/management/commands/dump_models.py
schematools/contrib/django/management/commands/import_profiles.py
schematools/contrib/django/management/commands/import_publishers.py
schematools/contrib/django/management/commands/import_schemas.py
amsterdam_schema_tools-9.1.6.dist-info/METADATA
amsterdam_schema_tools-9.1.6.dist-info/WHEEL
amsterdam_schema_tools-9.1.6.dist-info/entry_points.txt
amsterdam_schema_tools-9.1.6.dist-info/top_level.txt
amsterdam_schema_tools-9.1.6.dist-info/RECORD
