Metadata-Version: 2.4
Name: amsterdam-schema-tools
Version: 9.1.6
Summary: Tools to work with Amsterdam Schema.
Home-page: https://github.com/amsterdam/schema-tools
Author: Team Data Diensten, van het Dataplatform onder de Directie Digitale Voorzieningen (Gemeente Amsterdam)
Author-email: datapunt@amsterdam.nl
License: Mozilla Public 2.0
Keywords: jsonschema,schema,json,amsterdam,validation,code-generation
Classifier: Development Status :: 5 - Production/Stable
Classifier: License :: OSI Approved :: Mozilla Public License 2.0 (MPL 2.0)
Classifier: Programming Language :: Python
Classifier: Programming Language :: Python :: 3.10
Classifier: Programming Language :: Python :: 3.11
Classifier: Programming Language :: Python :: 3.12
Classifier: Programming Language :: Python :: 3.13
Classifier: Programming Language :: Python :: 3.14
Requires-Python: >=3.10
License-File: LICENSE
Requires-Dist: sqlalchemy>=2.0.40
Requires-Dist: geoalchemy2
Requires-Dist: psycopg
Requires-Dist: pg-grant
Requires-Dist: click
Requires-Dist: deepdiff
Requires-Dist: jsonlines
Requires-Dist: jsonschema[format]>=3.2.0
Requires-Dist: shapely>=1.8.0
Requires-Dist: python-string-utils
Requires-Dist: python-dateutil
Requires-Dist: requests
Requires-Dist: jinja2
Requires-Dist: mappyfile
Requires-Dist: jsonpath-rw
Requires-Dist: orjson
Requires-Dist: more-ds
Requires-Dist: factory_boy
Requires-Dist: remote-pdb
Requires-Dist: more-itertools
Provides-Extra: tests
Requires-Dist: types-requests; extra == "tests"
Requires-Dist: types-click; extra == "tests"
Requires-Dist: types-python-dateutil; extra == "tests"
Requires-Dist: flake8; extra == "tests"
Requires-Dist: flake8-colors; extra == "tests"
Requires-Dist: flake8-raise; extra == "tests"
Requires-Dist: flake8-bandit; extra == "tests"
Requires-Dist: flake8-bugbear; extra == "tests"
Requires-Dist: flake8-builtins; extra == "tests"
Requires-Dist: flake8-comprehensions; extra == "tests"
Requires-Dist: flake8-docstrings; extra == "tests"
Requires-Dist: flake8-implicit-str-concat; extra == "tests"
Requires-Dist: flake8-print; extra == "tests"
Requires-Dist: flake8-rst; extra == "tests"
Requires-Dist: flake8-string-format; extra == "tests"
Requires-Dist: flake8-logging-format; extra == "tests"
Requires-Dist: pytest; extra == "tests"
Requires-Dist: pytest-cov; extra == "tests"
Requires-Dist: pytest-django>=4.7.0; extra == "tests"
Requires-Dist: pytest-sqlalchemy; extra == "tests"
Requires-Dist: sqlalchemy-utils==0.41.2; extra == "tests"
Provides-Extra: django
Requires-Dist: django!=5.0,!=5.1,<6.0,>=4.2; extra == "django"
Requires-Dist: django-gisserver>=1.2.7; extra == "django"
Requires-Dist: django-environ; extra == "django"
Requires-Dist: factory_boy; extra == "django"
Provides-Extra: dev
Requires-Dist: build; extra == "dev"
Requires-Dist: twine; extra == "dev"
Provides-Extra: kafka
Requires-Dist: confluent-kafka; extra == "kafka"
Dynamic: license-file
